<?xml version="1.0"?>

<xfeEditor>
<menu1>
	<newfile visible="true">新しいドキュメント</newfile>	
	<savefile visible="true">ファイルの保存</savefile>
	<print visible="true">印刷</print>
	<pagebreak visible="true">ページ分割</pagebreak>
	
	<split/>
	
	<cut visible="true">カット</cut>
	<copy visible="true">コピー</copy>
	<paste visible="true">貼り付け</paste>
	
	<split/>
		
	<Undo visible="true">元に戻す</Undo>
	<Redo visible="true">再度実行して</Redo>
	
	<split/>
	
	<InsertHyperlink visible="true">ハイパーリンクの挿入</InsertHyperlink>
	<RemoveHyperlink visible="true">ハイパーリンクの削除</RemoveHyperlink>
	
	<split/>
	
	<InsertImage visible="true">画像の挿入</InsertImage>
	<ImageProperty visible="true">画像編集</ImageProperty>
	
	<split/>
	
	<InsertFlash visible="true">Flashの挿入</InsertFlash>
	<InsertMedia visible="true">動画の挿入</InsertMedia>
	<InsertMediaLink visible="true">外部ビデオの挿入</InsertMediaLink>
	<Background visible="false">ビデオの挿入</Background>
	<InsertGrid visible="false">グリッド挿入</InsertGrid>
	
	
	<split/>
	
	<InsertSymbol visible="true">記号を挿入</InsertSymbol>
	<HorizontalRule visible="true">水平線の挿入</HorizontalRule>
	<Bookmark visible="false">ブックマークの挿入</Bookmark>		
	
	<split/>
	
	<Search visible="true">検索</Search>
	<Replace visible="true">置換</Replace>
	
	<split/>	
	
	<SelectAll visible="true">すべて選択</SelectAll>
	
	<split/>
	
	<layout visible="true">レイアウト</layout>
	
	<split/>			
	
	<FullScreen visible="true">フルスクリーン</FullScreen>
	
		
</menu1>
<menu2>
	
	
	<inserttable visible="true">表の挿入</inserttable>
	<drawtable visible="true">表の描画</drawtable>
	
	<split/>
	
	<insertrowabove visible="true">上に行を追加する</insertrowabove>
	<insertrowbelow visible="true">下に行を追加</insertrowbelow>
	<insertcolumnleft visible="true">左に列を追加する</insertcolumnleft>
	<insertcolumnright visible="true">右側に列を追加する</insertcolumnright>
	<deleterow visible="true">行を削除する</deleterow>
	<deletecolumn visible="true">列の削除</deletecolumn>
	
	<split/>
	
	<mergecell visible="true">セルの結合</mergecell>
	<splitcell visible="true">セルの分割</splitcell>
	
	<split/>
		
	<tableproperty visible="true">テーブルのプロパティ</tableproperty>
	<cellproperty visible="true">セルのプロパティ</cellproperty>	
	
	<split/>
		
	<group>
		<aligntop visible="true">上揃え</aligntop>
		<alignmiddle visible="true">中央揃え</alignmiddle>
		<alignbottom visible="true">下揃え</alignbottom>
	</group>
	
	<group>
		<AlignLeft visible="true">左揃え</AlignLeft>
		<AlignCenter visible="true">中央揃え</AlignCenter>	
		<AlignRight visible="true">右揃え</AlignRight>
		<Justify visible="true">両端揃え</Justify>	
	</group>
			
	<group>
		<DecreaseIndent visible="true">インデント</DecreaseIndent>
		<IncreaseIndent visible="true">インデント</IncreaseIndent>
	</group>
	
	<group>
		<Superscript visible="true">上付き文字</Superscript>
		<Subscript visible="true">下付き文字</Subscript>	
	</group>	
	
	<group>
		<Numbering visible="true">番号付け</Numbering>
		<Bullets visible="true">箇条書き</Bullets>
	</group>			
</menu2>
<menu3>
	<Template visible="true">
		<!-- 불러올 양식들을 설정 해줍니다. -->
		<!-- ie 의 경우 경로 또는 파일명이 한글일 경우 불러오지 못합니다. -->
		<!-- xhtml 문법에 어긋나는 문서는 에러 메세지가 발생 할 수 있습니다. -->
		<item title="履歴書" show="true">
			http://192.168.0.156:55/eclipse_workspace/xfree_new/branches/source_rebuild/ex_documents/doc1.html			
		</item>
		<item title="ジャーナル" show="true">
			http://192.168.0.156:55/eclipse_workspace/xfree_new/branches/source_rebuild/ex_documents/doc2.htm
		</item>
		<item title="事業計画書" show="true">
			http://192.168.0.156:55/eclipse_workspace/xfree_new/branches/source_rebuild/ex_documents/doc3.htm
		</item>		
		<item title="給与支給明細書" show="true">
			http://192.168.0.156:55/eclipse_workspace/xfree_new/branches/source_rebuild/ex_documents/doc4.htm
		</item>
		<item title="公文書フォーム" show="true">
			http://192.168.0.156:55/eclipse_workspace/xfree_new/branches/source_rebuild/ex_documents/doc5.htm
		</item>		
		<item title="起案か" show="true">
			http://192.168.0.156:55/eclipse_workspace/xfree_new/branches/source_rebuild/ex_documents/doc6.htm			
		</item>
		<!--<item title="입사지원서" show="true">
			http://192.168.0.1/test.html			
		</item>-->
		<!--<item title="업무일지" show="true"></item>-->
		<!--<item title="소프트웨어신청서" show="true"></item>-->
		<!--<item title="표준검사신청서" show="true"></item>-->
		<!--<item title="업무협조" show="true"></item>-->
		<!--<item title="출장품의서" show="true"></item>-->		
	</Template>	
	
	
	<Fontfamily visible="true">フォントの種類</Fontfamily>
	<Fontsize visible="true">フォントサイズ</Fontsize>
	<LineHeight visible="true">行間隔</LineHeight>
	<LetterSpacing visible="true">文字の間隔</LetterSpacing>
	
	<group>
		<Bold visible="true">太字</Bold>
		<Italic visible="true">斜体</Italic>
		<Underline visible="true">下線</Underline>
		<Strikethrough visible="true">取り消し線</Strikethrough>		
	</group>
	<group>	
		<fontcolor visible="true">文字色</fontcolor>
		<fontbgcolor visible="true">テキストの背景色</fontbgcolor>
		<RemoveFormatting visible="true">フォーマットを削除</RemoveFormatting>	
	</group>
	
	<AdminLock visible="true">書き込み領域の設定</AdminLock>
	<AdminUnlock visible="true">書き込み領域を解除</AdminUnlock>		
	<Userguide visible="true">ユーザーヘルプ</Userguide>
	<about visible="true">製品情報</about>
</menu3>
</xfeEditor>